trauts/__init__.py
trauts/cli.py
trauts-0.0.2.dist-info/LICENSE
trauts-0.0.2.dist-info/METADATA
trauts-0.0.2.dist-info/WHEEL
trauts-0.0.2.dist-info/entry_points.txt
trauts-0.0.2.dist-info/top_level.txt
trauts-0.0.2.dist-info/RECORD
