Metadata-Version: 2.1
Name: trauts
Version: 0.0.2
Summary: A side project
Home-page: https://github.com/dim1tri/trauts
Author: dim1tri
Author-email: dim1tri@mailinator.com
License: UNKNOWN
Project-URL: Bug Tracker, https://github.com/dim1tri/trauts/issues
Platform: UNKNOWN
Classifier: Programming Language :: Python :: 3
Classifier: License :: OSI Approved :: MIT License
Classifier: Operating System :: OS Independent
Requires-Python: >=3.6
License-File: LICENSE
Requires-Dist: geohash2 (>=1.0)
Requires-Dist: fire (>=0.4.0)
